README.rst
setup.cfg
setup.py
ectou_metadata/__init__.py
ectou_metadata/service.py
ectou_metadata.egg-info/PKG-INFO
ectou_metadata.egg-info/SOURCES.txt
ectou_metadata.egg-info/dependency_links.txt
ectou_metadata.egg-info/entry_points.txt
ectou_metadata.egg-info/requires.txt
ectou_metadata.egg-info/top_level.txt