Metadata-Version: 1.1
Name: ectou-metadata
Version: 1.0.2
Summary: Yet another EC2 instance metadata mocking service.
Home-page: https://github.com/monetate/ectou-metadata
Author: Monetate
Author-email: jjpersch@monetate.com
License: MIT
Keywords: aws instance metadata
Platform: UNKNOWN
Classifier: Development Status :: 4 - Beta
Classifier: Intended Audience :: Developers
Classifier: License :: OSI Approved :: MIT License
Classifier: Programming Language :: Python :: 2.7
Classifier: Programming Language :: Python :: 3
